{"1": {"service": {"timestamp": 1670804718, "datetime": "2022-12-12T09:25:18.000Z"}, "data": [{"service": {"timestamp": 1670804718183, "mongoObjId": "639674efdfd7ff4b47dd9d8a", "metric": "mokil-ms.camera.context", "deviceId": "1", "algorithm": {"component": "KoreaUnivHumanAct-RTT", "version": "0.1"}}, "data": {"objects": [{"id": "54956", "class": "human", "pos2dMap": {"x": 75.68, "y": 51.52}, "status": [{"class": "action", "type": "walk"}]}, {"id": "55073", "class": "human", "pos2dMap": {"x": 52.12, "y": 35.82}, "status": [{"class": "action", "type": "walk"}]}, {"id": "55067", "class": "human", "pos2dMap": {"x": 30.91, "y": 87.31}, "status": [{"class": "action", "type": "walk"}]}, {"id": "55077", "class": "human", "pos2dMap": {"x": 29.65, "y": 84.83}, "status": [{"class": "action", "type": "walk"}]}, {"id": "55078", "class": "human", "pos2dMap": {"x": 46.36, "y": 53.69}, "status": [{"class": "action", "type": "walk"}]}, {"id": "55057", "class": "human", "pos2dMap": {"x": 80.54, "y": 27.54}, "status": [{"class": "action", "type": "walk"}]}, {"id": "55076", "class": "human", "pos2dMap": {"x": 55.72, "y": 12.77}, "status": [{"class": "action", "type": "walk"}]}, {"id": "55083", "class": "human", "pos2dMap": {"x": 31.08, "y": 83.49}, "status": [{"class": "action", "type": "walk"}]}, {"id": "55064", "class": "human", "pos2dMap": {"x": 73.08, "y": 27.79}, "status": [{"class": "action", "type": "walk"}]}], "meta": {"objNumber": {"human": 9}}}}, {"service": {"timestamp": 1670804718382, "mongoObjId": "639674efdfd7ff4b47dd9d8b", "metric": "mokil-ms.camera.context", "deviceId": "1", "algorithm": {"component": "KoreaUnivHumanAct-RTT", "version": "0.1"}}, "data": {"objects": [{"id": "54956", "class": "human", "pos2dMap": {"x": 75.67, "y": 51.3}, "status": [{"class": "action", "type": "walk"}]}, {"id": "55073", "class": "human", "pos2dMap": {"x": 52.39, "y": 34.93}, "status": [{"class": "action", "type": "walk"}]}, {"id": "55067", "class": "human", "pos2dMap": {"x": 30.96, "y": 87.17}, "status": [{"class": "action", "type": "walk"}]}, {"id": "55077", "class": "human", "pos2dMap": {"x": 29.94, "y": 84.79}, "status": [{"class": "action", "type": "walk"}]}, {"id": "55078", "class": "human", "pos2dMap": {"x": 46.65, "y": 52.48}, "status": [{"class": "action", "type": "walk"}]}, {"id": "55057", "class": "human", "pos2dMap": {"x": 80.38, "y": 27.41}, "status": [{"class": "action", "type": "walk"}]}, {"id": "55076", "class": "human", "pos2dMap": {"x": 55.74, "y": 12.85}, "status": [{"class": "action", "type": "walk"}]}, {"id": "55083", "class": "human", "pos2dMap": {"x": 31.88, "y": 84.01}, "status": [{"class": "action", "type": "walk"}]}, {"id": "55064", "class": "human", "pos2dMap": {"x": 73.01, "y": 26.94}, "status": [{"class": "action", "type": "walk"}]}], "meta": {"objNumber": {"human": 9}}}}, {"service": {"timestamp": 1670804718582, "mongoObjId": "639674efdfd7ff4b47dd9d8c", "metric": "mokil-ms.camera.context", "deviceId": "1", "algorithm": {"component": "KoreaUnivHumanAct-RTT", "version": "0.1"}}, "data": {"objects": [{"id": "54956", "class": "human", "pos2dMap": {"x": 75.7, "y": 51.08}, "status": [{"class": "action", "type": "walk"}]}, {"id": "55073", "class": "human", "pos2dMap": {"x": 52.87, "y": 33.64}, "status": [{"class": "action", "type": "walk"}]}, {"id": "55067", "class": "human", "pos2dMap": {"x": 30.96, "y": 86.98}, "status": [{"class": "action", "type": "walk"}]}, {"id": "55078", "class": "human", "pos2dMap": {"x": 46.73, "y": 51.45}, "status": [{"class": "action", "type": "walk"}]}, {"id": "55057", "class": "human", "pos2dMap": {"x": 80.21, "y": 27.23}, "status": [{"class": "action", "type": "walk"}]}, {"id": "55076", "class": "human", "pos2dMap": {"x": 55.66, "y": 12.53}, "status": [{"class": "action", "type": "walk"}]}, {"id": "55083", "class": "human", "pos2dMap": {"x": 31.98, "y": 84.41}, "status": [{"class": "action", "type": "walk"}]}, {"id": "55064", "class": "human", "pos2dMap": {"x": 72.94, "y": 25.66}, "status": [{"class": "action", "type": "walk"}]}], "meta": {"objNumber": {"human": 8}}}}, {"service": {"timestamp": 1670804718783, "mongoObjId": "639674efdfd7ff4b47dd9d8d", "metric": "mokil-ms.camera.context", "deviceId": "1", "algorithm": {"component": "KoreaUnivHumanAct-RTT", "version": "0.1"}}, "data": {"objects": [{"id": "54956", "class": "human", "pos2dMap": {"x": 75.74, "y": 50.97}, "status": [{"class": "action", "type": "walk"}]}, {"id": "55073", "class": "human", "pos2dMap": {"x": 53.36, "y": 32.21}, "status": [{"class": "action", "type": "walk"}]}, {"id": "55067", "class": "human", "pos2dMap": {"x": 31.18, "y": 86.84}, "status": [{"class": "action", "type": "walk"}]}, {"id": "55078", "class": "human", "pos2dMap": {"x": 47.3, "y": 50.37}, "status": [{"class": "action", "type": "walk"}]}, {"id": "55057", "class": "human", "pos2dMap": {"x": 80, "y": 26.81}, "status": [{"class": "action", "type": "walk"}]}, {"id": "55076", "class": "human", "pos2dMap": {"x": 55.6, "y": 12.25}, "status": [{"class": "action", "type": "walk"}]}, {"id": "55083", "class": "human", "pos2dMap": {"x": 32.71, "y": 84.85}, "status": [{"class": "action", "type": "walk"}]}, {"id": "55064", "class": "human", "pos2dMap": {"x": 72.98, "y": 24.96}, "status": [{"class": "action", "type": "walk"}]}], "meta": {"objNumber": {"human": 8}}}}, {"service": {"timestamp": 1670804718983, "mongoObjId": "639674efdfd7ff4b47dd9d8e", "metric": "mokil-ms.camera.context", "deviceId": "1", "algorithm": {"component": "KoreaUnivHumanAct-RTT", "version": "0.1"}}, "data": {"objects": [{"id": "54956", "class": "human", "pos2dMap": {"x": 75.75, "y": 50.55}, "status": [{"class": "action", "type": "walk"}]}, {"id": "55073", "class": "human", "pos2dMap": {"x": 53.78, "y": 31.09}, "status": [{"class": "action", "type": "walk"}]}, {"id": "55067", "class": "human", "pos2dMap": {"x": 30.67, "y": 86.57}, "status": [{"class": "action", "type": "walk"}]}, {"id": "55078", "class": "human", "pos2dMap": {"x": 47.64, "y": 49.11}, "status": [{"class": "action", "type": "walk"}]}, {"id": "55057", "class": "human", "pos2dMap": {"x": 79.81, "y": 26.4}, "status": [{"class": "action", "type": "walk"}]}, {"id": "55076", "class": "human", "pos2dMap": {"x": 55.46, "y": 12.07}, "status": [{"class": "action", "type": "walk"}]}, {"id": "55083", "class": "human", "pos2dMap": {"x": 32.82, "y": 85.35}, "status": [{"class": "action", "type": "walk"}]}, {"id": "55064", "class": "human", "pos2dMap": {"x": 73.07, "y": 24.5}, "status": [{"class": "action", "type": "walk"}]}], "meta": {"objNumber": {"human": 8}}}}]}}