{"1": {"service": {"timestamp": 1670804308, "datetime": "2022-12-12T09:18:28.000Z"}, "data": [{"service": {"timestamp": 1670804308000, "mongoObjId": "63967355dfd7ff4b47dd87f5", "metric": "mokil-ms.camera.context", "deviceId": "1", "algorithm": {"component": "KoreaUnivHumanAct-RTT", "version": "0.1"}}, "data": {"objects": [{"id": "54078", "class": "human", "pos2dMap": {"x": 55.41, "y": 92.34}, "status": [{"class": "action", "type": "walk"}]}, {"id": "54488", "class": "human", "pos2dMap": {"x": 26.31, "y": 19.04}, "status": [{"class": "action", "type": "walk"}]}, {"id": "54280", "class": "human", "pos2dMap": {"x": 28.54, "y": 37.85}, "status": [{"class": "action", "type": "walk"}]}, {"id": "54510", "class": "human", "pos2dMap": {"x": 54.92, "y": 11.17}, "status": [{"class": "action", "type": "walk"}]}, {"id": "54568", "class": "human", "pos2dMap": {"x": 51.56, "y": 43.1}, "status": [{"class": "action", "type": "walk"}]}, {"id": "54562", "class": "human", "pos2dMap": {"x": 58.34, "y": 38.35}, "status": [{"class": "action", "type": "walk"}]}, {"id": "54567", "class": "human", "pos2dMap": {"x": 29.73, "y": 59.38}, "status": [{"class": "action", "type": "walk"}]}, {"id": "54532", "class": "human", "pos2dMap": {"x": 24.95, "y": 47.44}, "status": [{"class": "action", "type": "walk"}]}, {"id": "54580", "class": "human", "pos2dMap": {"x": 56.49, "y": 71.42}, "status": [{"class": "action", "type": "walk"}]}, {"id": "54491", "class": "human", "pos2dMap": {"x": 50.82, "y": 36.93}, "status": [{"class": "action", "type": "walk"}]}, {"id": "54585", "class": "human", "pos2dMap": {"x": 28.12, "y": 62.49}, "status": [{"class": "action", "type": "walk"}]}], "meta": {"objNumber": {"human": 11}}}}, {"service": {"timestamp": 1670804308200, "mongoObjId": "63967355dfd7ff4b47dd87f6", "metric": "mokil-ms.camera.context", "deviceId": "1", "algorithm": {"component": "KoreaUnivHumanAct-RTT", "version": "0.1"}}, "data": {"objects": [{"id": "54078", "class": "human", "pos2dMap": {"x": 55.63, "y": 92.4}, "status": [{"class": "action", "type": "walk"}]}, {"id": "54488", "class": "human", "pos2dMap": {"x": 26.65, "y": 19.58}, "status": [{"class": "action", "type": "walk"}]}, {"id": "54280", "class": "human", "pos2dMap": {"x": 28.71, "y": 38.16}, "status": [{"class": "action", "type": "walk"}]}, {"id": "54510", "class": "human", "pos2dMap": {"x": 54.91, "y": 11.13}, "status": [{"class": "action", "type": "walk"}]}, {"id": "54568", "class": "human", "pos2dMap": {"x": 51.94, "y": 42.72}, "status": [{"class": "action", "type": "walk"}]}, {"id": "54562", "class": "human", "pos2dMap": {"x": 58.34, "y": 38.34}, "status": [{"class": "action", "type": "walk"}]}, {"id": "54567", "class": "human", "pos2dMap": {"x": 29.66, "y": 59.33}, "status": [{"class": "action", "type": "walk"}]}, {"id": "54532", "class": "human", "pos2dMap": {"x": 24.37, "y": 47.97}, "status": [{"class": "action", "type": "walk"}]}, {"id": "54580", "class": "human", "pos2dMap": {"x": 57.79, "y": 71.41}, "status": [{"class": "action", "type": "walk"}]}, {"id": "54491", "class": "human", "pos2dMap": {"x": 50.12, "y": 36.03}, "status": [{"class": "action", "type": "walk"}]}, {"id": "54585", "class": "human", "pos2dMap": {"x": 28.4, "y": 63.22}, "status": [{"class": "action", "type": "walk"}]}], "meta": {"objNumber": {"human": 11}}}}, {"service": {"timestamp": 1670804308400, "mongoObjId": "63967355dfd7ff4b47dd87f7", "metric": "mokil-ms.camera.context", "deviceId": "1", "algorithm": {"component": "KoreaUnivHumanAct-RTT", "version": "0.1"}}, "data": {"objects": [{"id": "54078", "class": "human", "pos2dMap": {"x": 55.69, "y": 92.42}, "status": [{"class": "action", "type": "walk"}]}, {"id": "54488", "class": "human", "pos2dMap": {"x": 26.94, "y": 20.13}, "status": [{"class": "action", "type": "walk"}]}, {"id": "54280", "class": "human", "pos2dMap": {"x": 29.57, "y": 39.15}, "status": [{"class": "action", "type": "walk"}]}, {"id": "54510", "class": "human", "pos2dMap": {"x": 54.9, "y": 11.1}, "status": [{"class": "action", "type": "walk"}]}, {"id": "54568", "class": "human", "pos2dMap": {"x": 52.38, "y": 41.98}, "status": [{"class": "action", "type": "walk"}]}, {"id": "54562", "class": "human", "pos2dMap": {"x": 58.34, "y": 38.34}, "status": [{"class": "action", "type": "walk"}]}, {"id": "54567", "class": "human", "pos2dMap": {"x": 29.63, "y": 59.34}, "status": [{"class": "action", "type": "walk"}]}, {"id": "54580", "class": "human", "pos2dMap": {"x": 58.22, "y": 71.46}, "status": [{"class": "action", "type": "walk"}]}, {"id": "54585", "class": "human", "pos2dMap": {"x": 28.47, "y": 63.79}, "status": [{"class": "action", "type": "walk"}]}, {"id": "54587", "class": "human", "pos2dMap": {"x": 36.56, "y": 57.78}, "status": [{"class": "action", "type": "walk"}]}], "meta": {"objNumber": {"human": 10}}}}, {"service": {"timestamp": 1670804308601, "mongoObjId": "63967355dfd7ff4b47dd87f8", "metric": "mokil-ms.camera.context", "deviceId": "1", "algorithm": {"component": "KoreaUnivHumanAct-RTT", "version": "0.1"}}, "data": {"objects": [{"id": "54078", "class": "human", "pos2dMap": {"x": 55.61, "y": 92.39}, "status": [{"class": "action", "type": "walk"}]}, {"id": "54488", "class": "human", "pos2dMap": {"x": 26.88, "y": 20.39}, "status": [{"class": "action", "type": "walk"}]}, {"id": "54280", "class": "human", "pos2dMap": {"x": 29.87, "y": 39.74}, "status": [{"class": "action", "type": "walk"}]}, {"id": "54510", "class": "human", "pos2dMap": {"x": 54.87, "y": 11.02}, "status": [{"class": "action", "type": "walk"}]}, {"id": "54568", "class": "human", "pos2dMap": {"x": 52.74, "y": 41.67}, "status": [{"class": "action", "type": "walk"}]}, {"id": "54562", "class": "human", "pos2dMap": {"x": 58.33, "y": 38.32}, "status": [{"class": "action", "type": "walk"}]}, {"id": "54567", "class": "human", "pos2dMap": {"x": 29.71, "y": 59.43}, "status": [{"class": "action", "type": "walk"}]}, {"id": "54580", "class": "human", "pos2dMap": {"x": 57.79, "y": 71.94}, "status": [{"class": "action", "type": "walk"}]}, {"id": "54587", "class": "human", "pos2dMap": {"x": 37.3, "y": 59.01}, "status": [{"class": "action", "type": "walk"}]}], "meta": {"objNumber": {"human": 9}}}}, {"service": {"timestamp": 1670804308801, "mongoObjId": "63967355dfd7ff4b47dd87f9", "metric": "mokil-ms.camera.context", "deviceId": "1", "algorithm": {"component": "KoreaUnivHumanAct-RTT", "version": "0.1"}}, "data": {"objects": [{"id": "54078", "class": "human", "pos2dMap": {"x": 55.69, "y": 92.39}, "status": [{"class": "action", "type": "stand"}]}, {"id": "54488", "class": "human", "pos2dMap": {"x": 27.24, "y": 21.1}, "status": [{"class": "action", "type": "stand"}]}, {"id": "54280", "class": "human", "pos2dMap": {"x": 30.13, "y": 40.34}, "status": [{"class": "action", "type": "walk"}]}, {"id": "54510", "class": "human", "pos2dMap": {"x": 54.86, "y": 11.02}, "status": [{"class": "action", "type": "walk"}]}, {"id": "54568", "class": "human", "pos2dMap": {"x": 53.06, "y": 41.33}, "status": [{"class": "action", "type": "walk"}]}, {"id": "54562", "class": "human", "pos2dMap": {"x": 58.32, "y": 38.31}, "status": [{"class": "action", "type": "walk"}]}, {"id": "54567", "class": "human", "pos2dMap": {"x": 29.8, "y": 59.57}, "status": [{"class": "action", "type": "walk"}]}, {"id": "54580", "class": "human", "pos2dMap": {"x": 57.8, "y": 72.37}, "status": [{"class": "action", "type": "walk"}]}, {"id": "54587", "class": "human", "pos2dMap": {"x": 37.65, "y": 60.16}, "status": [{"class": "action", "type": "walk"}]}, {"id": "54491", "class": "human", "pos2dMap": {"x": 47.77, "y": 34.65}, "status": [{"class": "action", "type": "walk"}]}], "meta": {"objNumber": {"human": 10}}}}]}}